obdii/__init__.py
obdii/basetypes.py
obdii/command.py
obdii/connection.py
obdii/errors.py
obdii/mode.py
obdii/protocol.py
obdii/py.typed
obdii/response.py
obdii/modes/__init__.py
obdii/modes/basetypes.py
obdii/modes/group_commands.py
obdii/modes/group_modes.py
obdii/modes/mode_01.py
obdii/modes/mode_02.py
obdii/modes/mode_03.py
obdii/modes/mode_04.py
obdii/modes/mode_09.py
obdii/modes/mode_at.py
obdii/parsers/__init__.py
obdii/parsers/formula.py
obdii/parsers/mappings.py
obdii/parsers/pids.py
obdii/protocols/__init__.py
obdii/protocols/protocol_base.py
obdii/protocols/protocol_can.py
obdii/protocols/protocol_j1850.py
obdii/protocols/protocol_kwp2000.py
obdii/transports/__init__.py
obdii/transports/transport_base.py
obdii/transports/transport_port.py
obdii/transports/transport_wifi.py
obdii/utils/__init__.py
obdii/utils/bits.py
obdii/utils/helper.py
obdii/utils/scan.py
py_obdii-0.9.1b0.dist-info/licenses/LICENSE
py_obdii-0.9.1b0.dist-info/METADATA
py_obdii-0.9.1b0.dist-info/WHEEL
py_obdii-0.9.1b0.dist-info/top_level.txt
py_obdii-0.9.1b0.dist-info/RECORD
