Metadata-Version: 2.4
Name: py-obdii
Version: 0.9.1b0
Summary: A Python library for interacting with OBDII.
Author: PaulMarisOUMary
License: MIT License
Project-URL: Home, https://github.com/PaulMarisOUMary/OBDII
Project-URL: Repository, https://github.com/PaulMarisOUMary/OBDII
Project-URL: Documentation, https://py-obdii.readthedocs.io
Project-URL: Issues, https://github.com/PaulMarisOUMary/OBDII/issues
Project-URL: Changelog, https://github.com/PaulMarisOUMary/OBDII/releases
Keywords: obd,obdii,obd2,py-obdii,py-obd2,python obd,ELM327,automotive,torque,car,vehicle,diagnostics,car diagnostics,engine data,car data,vehicle data,can bus
Classifier: Development Status :: 4 - Beta
Classifier: Intended Audience :: Developers
Classifier: Intended Audience :: Education
Classifier: License :: OSI Approved :: MIT License
Classifier: Natural Language :: English
Classifier: Operating System :: OS Independent
Classifier: Programming Language :: Python :: 3
Classifier: Programming Language :: Python :: 3 :: Only
Classifier: Programming Language :: Python :: 3.8
Classifier: Programming Language :: Python :: 3.9
Classifier: Programming Language :: Python :: 3.10
Classifier: Programming Language :: Python :: 3.11
Classifier: Programming Language :: Python :: 3.12
Classifier: Programming Language :: Python :: 3.13
Classifier: Programming Language :: Python :: 3.14
Classifier: Topic :: Scientific/Engineering :: Interface Engine/Protocol Translator
Classifier: Topic :: Software Development :: Embedded Systems
Classifier: Topic :: Software Development :: Libraries
Classifier: Topic :: Software Development :: Libraries :: Python Modules
Classifier: Topic :: System :: Monitoring
Classifier: Topic :: Utilities
Classifier: Typing :: Typed
Requires-Python: >=3.8
License-File: LICENSE
Requires-Dist: pyserial<4,>=3.5
Provides-Extra: test
Requires-Dist: pytest<8.4,>=8.3.5; extra == "test"
Requires-Dist: pytest-cov<6,>=5.0.0; extra == "test"
Requires-Dist: pytest-mock<3.15,>=3.14; extra == "test"
Provides-Extra: dev
Requires-Dist: ruff<1,>=0.14; extra == "dev"
Requires-Dist: ty<1,>=0.0.6; extra == "dev"
Provides-Extra: docs
Requires-Dist: sphinx<9,>=8.2; extra == "docs"
Requires-Dist: sphinx-autobuild; extra == "docs"
Requires-Dist: sphinxawesome-theme; extra == "docs"
Requires-Dist: sphinx-design; extra == "docs"
Provides-Extra: sim
Requires-Dist: ELM327-emulator<4,>=3; extra == "sim"
Dynamic: license-file
